calculator/Calculator.py
calculator/__init__.py
calculator/antlr4/CalculatorLexer.py
calculator/antlr4/CalculatorParser.py
calculator/antlr4/CalculatorParserListener.py
calculator/antlr4/CalculatorParserVisitor.py
calculator/common.py
calculator/grammar/CalculatorLexer.g4
calculator/grammar/CalculatorParser.g4
calculator/parser/CalculatorBailLexer.py
calculator/parser/CustomErrorListener.py
calculator/parser/__init__.py
gkcalculator.py
geekcamp_calculator-0.0.1.2.dist-info/LICENSE
geekcamp_calculator-0.0.1.2.dist-info/METADATA
geekcamp_calculator-0.0.1.2.dist-info/WHEEL
geekcamp_calculator-0.0.1.2.dist-info/entry_points.txt
geekcamp_calculator-0.0.1.2.dist-info/RECORD
