Metadata-Version: 2.1
Name: geekcamp-calculator
Version: 0.0.1.2
Summary: 基于 ANTLR4 编写的 Python 计算器 DEMO
Home-page: https://github.com/geekcampchina/geekcamp-calculator
Author: FifiLyu
Author-email: fifilyu@gmail.com
Requires-Python: >=3.8.5,<4.0.0
Classifier: Intended Audience :: Developers
Classifier: Operating System :: OS Independent
Classifier: Programming Language :: Python
Classifier: Programming Language :: Python :: 3
Classifier: Programming Language :: Python :: 3.9
Classifier: Programming Language :: Python :: 3.10
Classifier: Programming Language :: Python :: 3.11
Classifier: Topic :: System :: System Shells
Requires-Dist: antlr4-python3-runtime (>=4.13.1)
Requires-Dist: antlr4-tools (>=0.2)
Requires-Dist: happy-python (>=0.4.7)
Requires-Dist: pytest (>=7.4.1)
Project-URL: Documentation, https://github.com/geekcampchina/geekcamp-calculator
Project-URL: Repository, https://github.com/geekcampchina/geekcamp-calculator
